gachapy/__init__.py
gachapy/controller.py
gachapy/keylang.py
gachapy/loader.py
gachapy/objects.py
tests/__init__.py
tests/test_controller.py
tests/test_keylang.py
tests/test_objects.py
gachapy-1.0.0.dist-info/LICENSE
gachapy-1.0.0.dist-info/METADATA
gachapy-1.0.0.dist-info/WHEEL
gachapy-1.0.0.dist-info/top_level.txt
gachapy-1.0.0.dist-info/RECORD
